bsicon/__init__.py
bsicon/apps.py
bsicon/fields.py
bsicon/urls.py
bsicon/views.py
bsicon/widgets.py
bsicon/static/bsicon/bootstrap-icons-metadata.json
bsicon/static/bsicon/css/bootstrap-icons.css
bsicon/static/bsicon/css/bootstrap-icons.min.css
bsicon/static/bsicon/css/bsicon.css
bsicon/static/bsicon/fonts/bootstrap-icons.woff
bsicon/static/bsicon/fonts/bootstrap-icons.woff2
bsicon/static/bsicon/js/bsicon.js
bsicon/static/bsicon/js/list.min.js
bsicon/templates/bsicon/icon_selector.html
bsicon/templates/bsicon/icon_selector_include.html
bsicon/templatetags/__init__.py
bsicon/templatetags/bsicon_tags.py
django_bsicon-0.1.1.dist-info/licenses/LICENSE
django_bsicon-0.1.1.dist-info/METADATA
django_bsicon-0.1.1.dist-info/WHEEL
django_bsicon-0.1.1.dist-info/top_level.txt
django_bsicon-0.1.1.dist-info/RECORD
