Metadata-Version: 2.4
Name: django-bsicon
Version: 0.1.1
Summary: Bootstrap Icons selector for Django Admin
Author-email: "Cuántica Ingeniería y Tecnología S.A.S." <cuantica@bit-wise.org>
License: MIT
Project-URL: Homepage, https://github.com/jhoriascos/django-bsicon
Project-URL: Documentation, https://github.com/jhoriascos/django-bsicon#readme
Project-URL: Issues, https://github.com/jhoriascos/django-bsicon/issues
Project-URL: Source, https://github.com/jhoriascos/django-bsicon
Keywords: django,bootstrap,icons,admin
Classifier: Development Status :: 4 - Beta
Classifier: Framework :: Django
Classifier: Framework :: Django :: 4.2
Classifier: Framework :: Django :: 5.0
Classifier: Intended Audience :: Developers
Classifier: Programming Language :: Python :: 3
Classifier: Programming Language :: Python :: 3.8
Classifier: Programming Language :: Python :: 3.9
Classifier: Programming Language :: Python :: 3.10
Classifier: Programming Language :: Python :: 3.11
Classifier: Programming Language :: Python :: 3.12
Classifier: Topic :: Internet :: WWW/HTTP
Classifier: Topic :: Software Development :: Libraries :: Python Modules
Requires-Python: >=3.8
License-File: LICENSE
Requires-Dist: Django>=4.2
Provides-Extra: dev
Requires-Dist: twine>=4.0.2; extra == "dev"
Requires-Dist: build>=0.10.0; extra == "dev"
Dynamic: license-file
